{
    "key": "group_5c1902d27fc8a",
    "title": "Woo to SFDC",
    "location": [
        [
            {
                "param": "options_page",
                "operator": "==",
                "value": "woo-to-sfdc-settings"
            }
        ]
    ],
    "menu_order": 0,
    "position": "normal",
    "style": "default",
    "label_placement": "top",
    "instruction_placement": "label",
    "hide_on_screen": "",
    "active": 1,
    "description": "",
    "fields": [
        {
            "key": "field_5c23974a8b847",
            "label": "API Integration Credentials",
            "name": "",
            "type": "tab",
            "instructions": "",
            "required": 0,
            "conditional_logic": 0,
            "wrapper": {
                "width": "",
                "class": "",
                "id": ""
            },
            "placement": "top",
            "endpoint": 0
        },
        {
            "key": "field_5c23975b8b848",
            "label": "API Username",
            "name": "woo_to_sfdc_api_creds_username",
            "type": "text",
            "instructions": "",
            "required": 0,
            "conditional_logic": 0,
            "wrapper": {
                "width": "30",
                "class": "",
                "id": ""
            },
            "default_value": "",
            "placeholder": "",
            "prepend": "",
            "append": "",
            "maxlength": ""
        },
        {
            "key": "field_5c23976d8b849",
            "label": "API Password",
            "name": "woo_to_sfdc_api_creds_pwd",
            "type": "password",
            "instructions": "",
            "required": 0,
            "conditional_logic": 0,
            "wrapper": {
                "width": "30",
                "class": "",
                "id": ""
            },
            "placeholder": "",
            "prepend": "",
            "append": ""
        },
        {
            "key": "field_5c2397748b84a",
            "label": "API Token",
            "name": "woo_to_sfdc_api_creds_token",
            "type": "text",
            "instructions": "",
            "required": 0,
            "conditional_logic": 0,
            "wrapper": {
                "width": "30",
                "class": "",
                "id": ""
            },
            "default_value": "",
            "placeholder": "",
            "prepend": "",
            "append": "",
            "maxlength": ""
        },
        {
            "key": "field_5c1906e343ec0",
            "label": "Checkout Form",
            "name": "",
            "type": "tab",
            "instructions": "",
            "required": 0,
            "conditional_logic": 0,
            "wrapper": {
                "width": "",
                "class": "",
                "id": ""
            },
            "placement": "top",
            "endpoint": 0
        },
        {
            "key": "field_5c1902d543ebe",
            "label": "Woo to SFDC Field IDs",
            "name": "woo_to_sfdc_field_ids",
            "type": "repeater",
            "instructions": "",
            "required": 0,
            "conditional_logic": 0,
            "wrapper": {
                "width": "",
                "class": "",
                "id": ""
            },
            "collapsed": "",
            "min": 0,
            "max": 0,
            "layout": "table",
            "button_label": "",
            "sub_fields": [
                {
                    "key": "field_5c190836c73a2",
                    "label": "Woocommerce Field Name",
                    "name": "woo_to_sfdc_woo_field_name",
                    "type": "text",
                    "instructions": "",
                    "required": 0,
                    "conditional_logic": 0,
                    "wrapper": {
                        "width": "",
                        "class": "",
                        "id": ""
                    },
                    "default_value": "",
                    "placeholder": "",
                    "prepend": "",
                    "append": "",
                    "maxlength": ""
                },
                {
                    "key": "field_5c19084ac73a3",
                    "label": "SFDC Field ID",
                    "name": "woo_to_sfdc_sfdc_field_id",
                    "type": "text",
                    "instructions": "",
                    "required": 0,
                    "conditional_logic": 0,
                    "wrapper": {
                        "width": "",
                        "class": "",
                        "id": ""
                    },
                    "default_value": "",
                    "placeholder": "",
                    "prepend": "",
                    "append": "",
                    "maxlength": ""
                }
            ]
        },
        {
            "key": "field_5c224f1aff986",
            "label": "Countries & States Picklists",
            "name": "",
            "type": "tab",
            "instructions": "",
            "required": 0,
            "conditional_logic": 0,
            "wrapper": {
                "width": "",
                "class": "",
                "id": ""
            },
            "placement": "top",
            "endpoint": 0
        },
        {
            "key": "field_5c224f3cff988",
            "label": "SFDC Countries & Country Codes",
            "name": "woo_to_sfdc_countries",
            "type": "textarea",
            "instructions": "Refer to this snippet for a quick states extraction script from Salesforce: https:\/\/gist.github.com\/madebyted\/b953f93d84a3fde5b93f3c1017c69949",
            "required": 0,
            "conditional_logic": 0,
            "wrapper": {
                "width": "",
                "class": "",
                "id": ""
            },
            "default_value": "",
            "placeholder": "",
            "maxlength": "",
            "rows": "",
            "new_lines": ""
        },
        {
            "key": "field_5c224f29ff987",
            "label": "SFDC State per Country values",
            "name": "woo_to_sfdc_states",
            "type": "repeater",
            "instructions": "Refer to this snipped for a quick states extraction script from Salesforce: https:\/\/gist.github.com\/madebyted\/6b1e73c85e98868ed8f2acf195ea38b6",
            "required": 0,
            "conditional_logic": 0,
            "wrapper": {
                "width": "",
                "class": "",
                "id": ""
            },
            "collapsed": "",
            "min": 0,
            "max": 0,
            "layout": "table",
            "button_label": "",
            "sub_fields": [
                {
                    "key": "field_5c224f80ff989",
                    "label": "Country Code",
                    "name": "woo_to_sfdc_states_cc",
                    "type": "text",
                    "instructions": "",
                    "required": 0,
                    "conditional_logic": 0,
                    "wrapper": {
                        "width": "",
                        "class": "",
                        "id": ""
                    },
                    "default_value": "",
                    "placeholder": "",
                    "prepend": "",
                    "append": "",
                    "maxlength": ""
                },
                {
                    "key": "field_5c224fc6ec86a",
                    "label": "States Picklist",
                    "name": "woo_to_sfdc_states_picklist",
                    "type": "textarea",
                    "instructions": "",
                    "required": 0,
                    "conditional_logic": 0,
                    "wrapper": {
                        "width": "",
                        "class": "",
                        "id": ""
                    },
                    "default_value": "",
                    "placeholder": "",
                    "maxlength": "",
                    "rows": "",
                    "new_lines": ""
                }
            ]
        }
    ],
    "modified": 1557401638
}